{
    "title": "Heart's Medicine Hospital Heat",
    "description": "Enjoy this game for <b>FREE \u2013 or unlock ALL Original Stories games</b> with unlimited play and no ads by signing up for a <b>GHOS Subscription!</b>\r\n\r\nYour favorite doctor Allison is back in a gripping hospital time management game that you'll never forget! And neither will she... \ud83c\udfe5 \ud83d\ude91 \ud83d\udd25\r\n\r\n\u2764\ufe0f <b>PLAY THE EAGERLY AWAITED SEQUEL</b> to Heart's Medicine - Time to Heal and join your favorite doctor on a breathtaking new adventure\r\n\u2764\ufe0f <b>BECOME A DOCTOR</b> in 60 captivating time management levels and 30 extra challenge stages\r\n\u2764\ufe0f <b>DISCOVER 23 MINI-GAMES</b> and perform special treatments, like filling lungs with oxygen, focusing readouts and removing negative emotions\r\n\u2764\ufe0f <b>WITNESS A MEDICAL DRAMA</b> filled with romance, friendship, drama, and life-changing decisions\r\n\u2764\ufe0f <b>UPGRADE THE HOSPITAL</b> by completing levels and earning new equipment across 6 heated chapters\r\n\u2764\ufe0f <b>CATCH UP WITH THE CAST</b> and find out what's been going down with all your favorite characters from Little Creek Hospital\r\n\u2764\ufe0f <b>COMPLETE SPECIAL CHALLENGES</b> and collect diamonds to decorate Allison's apartment\r\n\u2764\ufe0f <b>ENJOY MANY EXTRAS</b> like competing against your friends in an endless level\r\n\r\nReady to find out what drama <b>Heart's Medicine - Hospital Heat</b> will bring our beloved doctor? \ud83d\udc69\u200d\u2695\ufe0f\r\n\r\nThis season picks up right after the previous compelling adventure. Things finally seem to have calmed down at Little Creek Hospital... \ud83c\udfe5\r\n\r\nBut not for long! When Allison receives a phone call from her mother, she doesn't know what to think. She hasn't seen her mom in over 20 years! Why would she contact Allison after all this time? And what could she want? Allison is left with no choice other than to face her past, in order to discover her future... \r\nWill she have the strength to cope with everything that has happened and all that is yet to come? There's only one way to find out... \r\n\r\n<b>Help Allison face her tragic past in this fiery hospital time management game!</b> \ud83d\udc89 \ud83d\ude91 \ud83d\udd25\r\n\r\n<b>*NEW!* Enjoy all GameHouse Original Stories with a subscription!</b> As long as you\u2019re a member, you can play all of your favorite story games. Relive past stories and fall in love with new ones. It\u2019s all possible with a GameHouse Original Stories subscription. Subscribe today!",
    "descriptionHTML": "Enjoy this game for <b>FREE \u2013 or unlock ALL Original Stories games</b> with unlimited play and no ads by signing up for a <b>GHOS Subscription!</b><br><br>Your favorite doctor Allison is back in a gripping hospital time management game that you&#39;ll never forget! And neither will she... \ud83c\udfe5 \ud83d\ude91 \ud83d\udd25<br><br>\u2764\ufe0f <b>PLAY THE EAGERLY AWAITED SEQUEL</b> to Heart&#39;s Medicine - Time to Heal and join your favorite doctor on a breathtaking new adventure<br>\u2764\ufe0f <b>BECOME A DOCTOR</b> in 60 captivating time management levels and 30 extra challenge stages<br>\u2764\ufe0f <b>DISCOVER 23 MINI-GAMES</b> and perform special treatments, like filling lungs with oxygen, focusing readouts and removing negative emotions<br>\u2764\ufe0f <b>WITNESS A MEDICAL DRAMA</b> filled with romance, friendship, drama, and life-changing decisions<br>\u2764\ufe0f <b>UPGRADE THE HOSPITAL</b> by completing levels and earning new equipment across 6 heated chapters<br>\u2764\ufe0f <b>CATCH UP WITH THE CAST</b> and find out what&#39;s been going down with all your favorite characters from Little Creek Hospital<br>\u2764\ufe0f <b>COMPLETE SPECIAL CHALLENGES</b> and collect diamonds to decorate Allison&#39;s apartment<br>\u2764\ufe0f <b>ENJOY MANY EXTRAS</b> like competing against your friends in an endless level<br><br>Ready to find out what drama <b>Heart&#39;s Medicine - Hospital Heat</b> will bring our beloved doctor? \ud83d\udc69\u200d\u2695\ufe0f<br><br>This season picks up right after the previous compelling adventure. Things finally seem to have calmed down at Little Creek Hospital... \ud83c\udfe5<br><br>But not for long! When Allison receives a phone call from her mother, she doesn&#39;t know what to think. She hasn&#39;t seen her mom in over 20 years! Why would she contact Allison after all this time? And what could she want? Allison is left with no choice other than to face her past, in order to discover her future... <br>Will she have the strength to cope with everything that has happened and all that is yet to come? There&#39;s only one way to find out... <br><br><b>Help Allison face her tragic past in this fiery hospital time management game!</b> \ud83d\udc89 \ud83d\ude91 \ud83d\udd25<br><br><b>*NEW!* Enjoy all GameHouse Original Stories with a subscription!</b> As long as you\u2019re a member, you can play all of your favorite story games. Relive past stories and fall in love with new ones. It\u2019s all possible with a GameHouse Original Stories subscription. Subscribe today!",
    "summary": "Remember that time you wanted to be a Doctor?",
    "installs": "5,000,000+",
    "minInstalls": 5000000,
    "realInstalls": 8273659,
    "score": 4.521739,
    "ratings": 84077,
    "reviews": 2227,
    "histogram": [
        5316,
        1823,
        3646,
        6082,
        67163
    ],
    "price": 0,
    "free": true,
    "currency": "USD",
    "sale": false,
    "saleTime": null,
    "originalPrice": null,
    "saleText": null,
    "offersIAP": true,
    "inAppProductPrice": "$1.99 - $89.99 per item",
    "developer": "GameHouse Original Stories",
    "developerId": "8768606447367526700",
    "developerEmail": "ghos@gamehouse.com",
    "developerWebsite": "http://www.gamehouseoriginalstories.com/",
    "developerAddress": "Lichttoren 32\n5611 BJ Eindhoven.\nThe Netherlands",
    "privacyPolicy": "https://www.gamehouseoriginalstories.com/static/privacy-policy.html",
    "genre": "Casual",
    "genreId": "GAME_CASUAL",
    "categories": [
        {
            "name": "Simulation",
            "id": "GAME_SIMULATION"
        },
        {
            "name": "Time management",
            "id": null
        },
        {
            "name": "Casual",
            "id": "GAME_CASUAL"
        },
        {
            "name": "Single player",
            "id": null
        },
        {
            "name": "Stylized",
            "id": null
        },
        {
            "name": "Hospital",
            "id": null
        },
        {
            "name": "Offline",
            "id": null
        }
    ],
    "icon": "https://play-lh.googleusercontent.com/7fwcNHXHhUxYTBW5ZnsYmyTguog7jzza58CqMFyrjWBOGThAamEfMDLs1QIqnKZjW9c",
    "headerImage": "https://play-lh.googleusercontent.com/ycETLWnMSaEnJ4u3NEuvbUz4ulB9H9CBUohN_xBn73jv1Rv8xm-DH76_hJSBnCV8tzk",
    "screenshots": [
        "https://play-lh.googleusercontent.com/Qm1xYhruurGQfjRmO-wucf44HFmEcBQZygWEZ_57ikjCLepsXxjiXa1lSUUtxsko72c",
        "https://play-lh.googleusercontent.com/tloTY_1f0md4UMMWA5iFd6Ig1c_wRfxX2TRn4ghKpdHnKrYKMZtzQO7QntpM-zt0BaXV",
        "https://play-lh.googleusercontent.com/JugMyv4Jc0iRnf8Nl57k1MpRtE3qbsBFwf2_rYTWrcy9sb1jTVB7q9gWam7VUM883W0",
        "https://play-lh.googleusercontent.com/DhIDd85-9iIRRHA7maYVPOBb_Xzj4H88vl2z6RJ-5LyBd13nVEFaWJeGPbepepICrw",
        "https://play-lh.googleusercontent.com/RuwQ0jHb2VpSi_ETiGj5TOw4GdYh8Ah3NP34BUjzfyMuPdeoD1jz9lt5BbihWply9Q",
        "https://play-lh.googleusercontent.com/r_VVPs_ZSxEyt54-cmYajdlQWfFLY2WWB00s1Tpk1dvxRiRNjcXa9gQsbaisq276ODQ",
        "https://play-lh.googleusercontent.com/GI7s9lR5-t4ZkRaGREzxM9m85WhpOY7U05z74UzBDb6XWKYT4ua-VBf6-qj35qVzR5o",
        "https://play-lh.googleusercontent.com/wfo9ylH-aqmyoPjBPD94VWfbEHZDsgU9-SKwRCeZf6bO18e_v9tPsg_PcNHlRm0sOoc",
        "https://play-lh.googleusercontent.com/j07MAITaitlsYO0J9hrBVPGhPV38oxUBaR3qTZYmCa3Fur9E0Ov3enI3AEznRFN7Ex8",
        "https://play-lh.googleusercontent.com/ikNQozx_OSqKl9F4zkYxJOaoCEEx-2SoJKwNnKI6_rGoBFSTGb7iTBwXv3yXvgT9cQ",
        "https://play-lh.googleusercontent.com/4VTLYZOLDOF-L6DyvzOxuYmILEQscIvnAS2_-jM1vKyIO8QWcLaoEg14LuV6kppG_wzd",
        "https://play-lh.googleusercontent.com/ZOTqTMZRKA410TX1YBwx0nO4IvYOc0DGE5S7kPfmz0Hzkp49Wu305Rv0RCZ5VXQ33w",
        "https://play-lh.googleusercontent.com/3yt2rfP0XwtwIOI7QQO9Di7KX6sLlgbdnqL7IzT8dPsfHsjbPhYNOusyr2MUOk1hNoI",
        "https://play-lh.googleusercontent.com/Jax5fXLITh-H3QtTLeLy1lMZkrSIXDplMXslser5xjyvV5RZ0-Asdc5W750QhB3dC1w",
        "https://play-lh.googleusercontent.com/1h3K6OG3PEjcsFkReW70r28zHatg9y-tPOnzcrYcjAWAwnW0vgdrJUSVxrUP73vXWXl0"
    ],
    "video": "https://www.youtube.com/embed/YmQPdGmaxcQ?ps=play&vq=large&rel=0&autohide=1&showinfo=0",
    "videoImage": "https://play-lh.googleusercontent.com/ycETLWnMSaEnJ4u3NEuvbUz4ulB9H9CBUohN_xBn73jv1Rv8xm-DH76_hJSBnCV8tzk",
    "contentRating": "Everyone 10+",
    "contentRatingDescription": "Fantasy Violence",
    "adSupported": true,
    "containsAds": true,
    "released": "May 18, 2017",
    "lastUpdatedOn": "Sep 20, 2024",
    "updated": 1726848422,
    "version": "6.9",
    "comments": [],
    "appId": "com.gamehouse.hm3gp",
    "url": "https://play.google.com/store/apps/details?id=com.gamehouse.hm3gp&hl=en&gl=us"
}