{
    "title": "Handtevy Mobile",
    "description": "Handtevy Mobile is a vital ally for healthcare professionals, offering rapid, precise medication dosing and equipment information critical for emergency care. Designed to support both pediatric and adult patients, and tailored to your guidelines, Handtevy enables comprehensive protocol management and real-time documentation, seamlessly integrated with leading ePCR platforms.\r\n\r\nFeatures such as CPR timers, detailed protocols, and checklists, facilitate decisive actions,  enhancing patient outcomes. CPR Assist aids high-performance teams during cardiac arrests by providing agency-specific timers and audio-visual cues that guide treatment and reassessment.\r\n\r\nThe addition of Handtevy Connect further streamlines medical communication, ensuring your  contacts and directions are easily accessible. With Handtevy, practitioners have access to powerful, life-saving tools, boosting confidence and precision in every emergency response.",
    "descriptionHTML": "Handtevy Mobile is a vital ally for healthcare professionals, offering rapid, precise medication dosing and equipment information critical for emergency care. Designed to support both pediatric and adult patients, and tailored to your guidelines, Handtevy enables comprehensive protocol management and real-time documentation, seamlessly integrated with leading ePCR platforms.<br><br>Features such as CPR timers, detailed protocols, and checklists, facilitate decisive actions,  enhancing patient outcomes. CPR Assist aids high-performance teams during cardiac arrests by providing agency-specific timers and audio-visual cues that guide treatment and reassessment.<br><br>The addition of Handtevy Connect further streamlines medical communication, ensuring your  contacts and directions are easily accessible. With Handtevy, practitioners have access to powerful, life-saving tools, boosting confidence and precision in every emergency response.",
    "summary": "Rapidly dose and document care for critically ill and injured patients.",
    "installs": "50,000+",
    "minInstalls": 50000,
    "realInstalls": 50008,
    "score": 4.7,
    "ratings": 443,
    "reviews": 167,
    "histogram": [
        8,
        0,
        26,
        43,
        362
    ],
    "price": 0,
    "free": true,
    "currency": "USD",
    "sale": false,
    "saleTime": null,
    "originalPrice": null,
    "saleText": null,
    "offersIAP": false,
    "inAppProductPrice": null,
    "developer": "Pediatric Emergency Standards Inc.",
    "developerId": "5736913709144209105",
    "developerEmail": "info@handtevy.com",
    "developerWebsite": "https://www.handtevy.com",
    "developerAddress": "11860 W. State Road 84, Suite B1\nDavie, FL 33325",
    "privacyPolicy": "https://www.handtevy.com/privacy-policy/",
    "genre": "Medical",
    "genreId": "MEDICAL",
    "categories": [
        {
            "name": "Medical",
            "id": "MEDICAL"
        }
    ],
    "icon": "https://play-lh.googleusercontent.com/Hjbe2taSxC_8RkAC6_xxW9uWhSPErslG5XUaO42bANm5qO_rUwdaFiH5zSBdXzZnKuc",
    "headerImage": "https://play-lh.googleusercontent.com/UPZaQGFbhudnEZYUDpMaLbEJh2WelakIxOk4SanzkhmhbW5bri0qj-sQJWYK0BVsu2c",
    "screenshots": [
        "https://play-lh.googleusercontent.com/VkQ14Nscpd8p_D74e_GUJP-n28EcfKNig6TbbUwHzYc0F9qgalkEl5kO4kBmV4biwCY",
        "https://play-lh.googleusercontent.com/5iEIvm0d3klyq5dBvIeKp18RR2XxgQ-oOqzLrTbxvdjI1QVpu1Kpez8WI4O6ngqgyoDs",
        "https://play-lh.googleusercontent.com/wv00ybOC-JALTbNOZkR9NMkudR0xcgakkO1fTOFyXGXE4M-IxFMJW2YHM3PY0e1vqIs",
        "https://play-lh.googleusercontent.com/2Ozz0VRIf0eXDJDMdYnMzuJiJ7FQ_WXohbvh1fUSmxHbIIwGYeYflfupWk1fsr3zGDss",
        "https://play-lh.googleusercontent.com/1wkbLtVaB0o5TmhA3sx3GwLwMk2gLLshyc6UP0l6z7Yuv1rCkO1jqbKi_XCdFmw0-A",
        "https://play-lh.googleusercontent.com/BWjtQwgTTWSSK13bSlPpzAtUolr2ce4Z34KP9VzJHv3L8FSeXoM_bnCUXKGtxJzVCCw",
        "https://play-lh.googleusercontent.com/ThGnYslVKITQBSs8i4c7qIto_zKulfkoLgBb8ptygFUcigzcTtF0ggj_euNYOrzqUbkD",
        "https://play-lh.googleusercontent.com/RffcOMA9cP1ynBMot5Hs4torazEAbdwXNSgBA53PIGFTBHrVND1goRMg6d6iV2Zjd1v9",
        "https://play-lh.googleusercontent.com/Npd2d6KAZIgpNN-c025PUq2OkRb4aHdAuzsGbePHZqyxZf--MwzyrwTyzdnxRSCx_w",
        "https://play-lh.googleusercontent.com/J21_pSUVeyHgw0JAbdiMt7VZgCnUE4_8USrB6xpTpWYsuquiXQ0G3CksNH_iZVjFcOE",
        "https://play-lh.googleusercontent.com/v96yqifJM23bvdcqp0FCHszSryeeRpgK3WAA7pzWIa4i12fZSgaztE1rrTOcwLawVag",
        "https://play-lh.googleusercontent.com/l9dKm_sKGIXUyIDztAq9ya_uRz-r1vNgR2sJI-6p0lLablie2znA3S6N2w97AWgrLQ",
        "https://play-lh.googleusercontent.com/afFoj2KEUci4e3aHQmnDX9PnOdtUlR6iPPyApomZg_azsuTIvav9iCPsHSt1LXaNCR_N",
        "https://play-lh.googleusercontent.com/aEHlqDChjLd4gSuuMC5c0H3ryFsetOL-sO8rvB9tsv53nTIJAjdy8QcjYCo7MPqKNsE",
        "https://play-lh.googleusercontent.com/xjhpp2uVhe0HlkKk3nW8Q0-RD3oLKAeHpUvvPLfmsAx3Z8AAYDmMngE7Ra8c0OBBgA",
        "https://play-lh.googleusercontent.com/nOMhlyx_bClzNrjWtZq6ePWeChk9SbGuXEcSFsbZa7s91OTieCDUdy5AXxXnkOTSaslh",
        "https://play-lh.googleusercontent.com/WvJUJzPjIViO6git_-qrsyjBpxeh_A2wAbS0ceh0f29dR1Ja9DW18PBqSHS7JlGvTBI",
        "https://play-lh.googleusercontent.com/VI-ujZ0yzZO7-I23EuwxCVUBgi-abBjT1U303ZgCPcp-Nxxwvbq315X3szb3RC83HFw",
        "https://play-lh.googleusercontent.com/wZcp87YKSv6bTmeLfalYT_cMLP8EK6XnymD5RhJNvkRmKdJo5sVLplnG7zLNlb4qaoxq",
        "https://play-lh.googleusercontent.com/6wL9EKKNCoJlXbvBtMEN0VFGLfjLH8bMEYjm1Je40vx4HBKoh2zGxnkiLMfgxeOgx2qD",
        "https://play-lh.googleusercontent.com/mp9b5vtrHzZkEwS0FJ2_UUxuFKhuE5hdz2QfT0Og-Hk6qqM-HHCsATOtSagdU0FhHdo"
    ],
    "video": null,
    "videoImage": null,
    "contentRating": "Everyone",
    "contentRatingDescription": null,
    "adSupported": false,
    "containsAds": false,
    "released": "Sep 11, 2015",
    "lastUpdatedOn": "Oct 28, 2024",
    "updated": 1730138984,
    "version": "5.15.1",
    "comments": [],
    "appId": "com.oi.handtevy",
    "url": "https://play.google.com/store/apps/details?id=com.oi.handtevy&hl=en&gl=us"
}