{
    "title": "MSD Manual Guide to Obstetrics",
    "description": "SPECIAL NOTE ABOUT DOWNLOAD\r\n*** Downloading this app is a 2-step process: First the app template is downloaded, and then the app content is downloaded and installed. Please do not navigate away from the app until both steps have been completed. ***\r\n\r\nThe MSD Manual Guide to Obstetrics is a subset of the MSD Professional Manual.  This new app is intended for healthcare practitioners who take care of obstetric patients. It includes 99 clear, concise topics covering:\r\n\u2022\tNormal pregnancy and prenatal care\r\n\u2022\tEvaluation and management of symptoms and complications of pregnancy\r\n\u2022\tHigh-risk pregnancy\r\n\u2022\tNormal and complicated labor and delivery\r\n\u2022\tPostpartum care and complications\r\n\u2022\tInitial care of the newborn, including newborn resuscitation\r\n\u2022\tFamily planning and prenatal genetic counseling\r\n\r\nThe app also comes with: \r\n\u2022\t14 concise, instructional videos on how to do normal and complicated deliveries, manage postpartum hemorrhage, and do newborn resuscitation \r\n\u2022\tGestational age and due date calculator\r\n\r\n\r\nThe trusted MSD Manual Guide to Obstetrics is written and updated regularly by a dozen academic obstetricians and pediatricians. \r\n\r\nThe app is always free and has no advertising.\r\n\r\n\r\nAbout MSD Manuals\r\nOur mission is simple: \r\nWe believe that health information is a universal right and that every person is entitled to accurate, accessible and usable medical information. We have a responsibility to protect, preserve and share the best current medical information to enable more informed decisions, enhance relationships between patients and professionals, and improve health care outcomes around the world. \r\nThat\u2019s why we are making the MSD Manuals available for free in digital form to professionals and patients around the world. No registration or subscription required, and no ads. \r\n\r\nNOND-1179303-0001 04/16\r\nThis mobile application is intended for Healthcare Professionals.\r\nFor more information please read the End User License Agreement at \r\nhttps://www.msd.com/policy/terms-of-use/home.html\r\n\r\nFor more information about our privacy practices, please see our privacy commitment at https://www.msdprivacy.com \r\n\r\nAdverse Event Reporting:  To report an adverse event with a specific MSD product, please call the National Service Center at 1-800-672-6372. \r\nCountries outside the United States may have specific procedures in place to address reports of adverse events. Please contact your local MSD office or local health authority for more information.\r\n\r\nFor questions or help with the app, please contact msdmanualsinfo@msd.com",
    "descriptionHTML": "SPECIAL NOTE ABOUT DOWNLOAD<br>*** Downloading this app is a 2-step process: First the app template is downloaded, and then the app content is downloaded and installed. Please do not navigate away from the app until both steps have been completed. ***<br><br>The MSD Manual Guide to Obstetrics is a subset of the MSD Professional Manual.  This new app is intended for healthcare practitioners who take care of obstetric patients. It includes 99 clear, concise topics covering:<br>\u2022\tNormal pregnancy and prenatal care<br>\u2022\tEvaluation and management of symptoms and complications of pregnancy<br>\u2022\tHigh-risk pregnancy<br>\u2022\tNormal and complicated labor and delivery<br>\u2022\tPostpartum care and complications<br>\u2022\tInitial care of the newborn, including newborn resuscitation<br>\u2022\tFamily planning and prenatal genetic counseling<br><br>The app also comes with: <br>\u2022\t14 concise, instructional videos on how to do normal and complicated deliveries, manage postpartum hemorrhage, and do newborn resuscitation <br>\u2022\tGestational age and due date calculator<br><br><br>The trusted MSD Manual Guide to Obstetrics is written and updated regularly by a dozen academic obstetricians and pediatricians. <br><br>The app is always free and has no advertising.<br><br><br>About MSD Manuals<br>Our mission is simple: <br>We believe that health information is a universal right and that every person is entitled to accurate, accessible and usable medical information. We have a responsibility to protect, preserve and share the best current medical information to enable more informed decisions, enhance relationships between patients and professionals, and improve health care outcomes around the world. <br>That\u2019s why we are making the MSD Manuals available for free in digital form to professionals and patients around the world. No registration or subscription required, and no ads. <br><br>NOND-1179303-0001 04/16<br>This mobile application is intended for Healthcare Professionals.<br>For more information please read the End User License Agreement at <br>https://www.msd.com/policy/terms-of-use/home.html<br><br>For more information about our privacy practices, please see our privacy commitment at https://www.msdprivacy.com <br><br>Adverse Event Reporting:  To report an adverse event with a specific MSD product, please call the National Service Center at 1-800-672-6372. <br>Countries outside the United States may have specific procedures in place to address reports of adverse events. Please contact your local MSD office or local health authority for more information.<br><br>For questions or help with the app, please contact msdmanualsinfo@msd.com",
    "summary": "Stay up-to-date with the MSD Manual Guide to Obstetrics app.",
    "installs": "10,000+",
    "minInstalls": 10000,
    "realInstalls": 19788,
    "score": 5,
    "ratings": 138,
    "reviews": 2,
    "histogram": [
        0,
        0,
        0,
        0,
        138
    ],
    "price": 0,
    "free": true,
    "currency": "USD",
    "sale": false,
    "saleTime": null,
    "originalPrice": null,
    "saleText": null,
    "offersIAP": false,
    "inAppProductPrice": null,
    "developer": "Merck Sharp & Dohme LLC",
    "developerId": "Merck+Sharp+%26+Dohme+LLC",
    "developerEmail": "msdmanualsinfo@msd.com",
    "developerWebsite": "https://www.msdmanuals.com/professional/content/contact-us",
    "developerAddress": "126 East Lincoln Ave.\nP.O. Box 2000\nRahway,\nNew Jersey 07065\nUSA",
    "privacyPolicy": "https://www.msdprivacy.com",
    "genre": "Medical",
    "genreId": "MEDICAL",
    "categories": [
        {
            "name": "Medical",
            "id": "MEDICAL"
        }
    ],
    "icon": "https://play-lh.googleusercontent.com/rq7LOs34i2ozhXbVNdS3ankqItEFcETrBfaZrRYIi84bV_ytIGFEw2Si3BTdWnYdFw",
    "headerImage": "https://play-lh.googleusercontent.com/rXW4o32kljZWGz7dYzonRJWKLu0-yPIua_SwQYHjPeeX1HmZROvNx7OW6znJ3sMjGo8",
    "screenshots": [
        "https://play-lh.googleusercontent.com/Y1v0DiCq-JJjzUUwwgDOBJTn5M3_unZByMnmuGlFbMmn31ECm3Xr6LlWyjVFwfMxsJY",
        "https://play-lh.googleusercontent.com/sWbxIx_NThV0COtuJs7t3poxt3QNBP1JS6oKSSAGSmtbefsURb4RV-9BOqTZp-AakZM",
        "https://play-lh.googleusercontent.com/5PLKz1WXVEeh196A8jdOJAKy-mz-fcilLxEG-X4VP3aisU3oSJXosxJVaKICSh_RnQ",
        "https://play-lh.googleusercontent.com/j2zq4FLWI0_gb_IRBwErnAOY-xXKW2pf1-a61krAiFQX64wO-oi-i54A5HmrATNtw_Q",
        "https://play-lh.googleusercontent.com/DMGBlsoSHhv6H5uB6bauis3sCARi7tTMAsqT9mSBZKPwmogzNy06bMzL14nKHwvD7w",
        "https://play-lh.googleusercontent.com/h2dWDxhlLwODw0gfohLcxj96itx0dS47d1FTLxkSRV5fsW-07yTKVTqep0Q5v2Xvhlw",
        "https://play-lh.googleusercontent.com/u1T1UFUykx3TQI2JaxTeclKsQdFiMw6y2x1htD9t9Jan06TTu388z-aaWq_dLQcJOUk",
        "https://play-lh.googleusercontent.com/4r4TgL2ar658_Ab-IyethcFizgWdSY1wGEIiblQFlt-kSCCNBrurXRTiMleLxXwDvLw",
        "https://play-lh.googleusercontent.com/R2NgDqx9JbwVLpfFzRUePSI7yT6FQRkdKWDwyZQEaEnQ03dEOdJOJf2sQGy-Yr3u2rHR",
        "https://play-lh.googleusercontent.com/4wS27sAz-vKlCHzN0Z0oDytWjrIvsVdgx697XZeDX_g6FAC9zJXEd5RX4HeH3lBr_EM",
        "https://play-lh.googleusercontent.com/taPZZ-593T4ZDWCrRIR0utwUsHrjaiu0KFJGg1jNKSY6IFSzw2FxYSBDSgnhZVu60w",
        "https://play-lh.googleusercontent.com/AXApugeu6MWvSUi-4RVBSSKn3TZ0A3u20Nw2-P3X3z_-P_9ES2rR3DSPxPzFdBBVgSk",
        "https://play-lh.googleusercontent.com/jO38zHgbT7pf08OwrQ3ZotjyNPcPWHeifJFn0V2KlEXArb9uaAX8LqFOvv450Ya-AjU",
        "https://play-lh.googleusercontent.com/r51OieCqrGUUZ5DDTXLZi73oT5qJndi21YowD1WUr_zHaHWnZ5UrbsY7eeAaOkdy9g",
        "https://play-lh.googleusercontent.com/ieEuCQ5r4x0awUBRpBZeWf4fuZM2hmaVmhkkb89BvbxLQiP1PVPhIZSnG_Oe4DZNHIQ",
        "https://play-lh.googleusercontent.com/yD4awSZ4cvA65RYsNbr4pngHb0Ya7H62plFwzlOIExP3dI-DIPMy7rcqgGqKgUFqow"
    ],
    "video": null,
    "videoImage": null,
    "contentRating": "Everyone",
    "contentRatingDescription": null,
    "adSupported": false,
    "containsAds": false,
    "released": "Apr 6, 2020",
    "lastUpdatedOn": "Sep 26, 2024",
    "updated": 1727366257,
    "version": "1.8",
    "comments": [],
    "appId": "com.msd.obstetrics",
    "url": "https://play.google.com/store/apps/details?id=com.msd.obstetrics&hl=en&gl=us"
}