{
    "title": "Doctor31 - Symptom Checker",
    "description": "You are in the good place! \r\n\r\nDoctor31 is an application that helps you find out what diseases you may suffer from. \r\nYou can consult it at any time. Whether you are at work, at home or on vacation. Whenever you want.\r\n\r\nUse Doctor31 now to find out what your health condition is.\r\nUse Doctor31 when you are not feeling well and find out what diseases you may be suffering from.\r\nUse when you have blood, urine or stool tests results. Find out what they indicate.\r\n\r\nReliable information.\r\nDoctor31 is created by doctors and uses the necessary information for them to obtain the right to practice in different specialties.\r\n\r\nEasy to use.\r\nDownload the application and it is ready to use. You do not need an account, email or credit card.\r\n\r\nSafe!\r\nYou use the application without any account or personal data that may lead to your identification.\r\n\r\nPersonalized information.\r\nWe provide you with information based on your symptoms, age, gender and medical history. We are all different from each other. That's why you receive information that suits you.\r\n\r\nIt's like a digital \u201cGeneral Practitioner (GP)\u201d on your phone.\r\nIt is a super doctor, having knowledge ranging from family medicine to surgery, from cardiology to dermatology. 31 main medical specialties. It helps you to keep calm, being informed whenever you want about your possible personal medical condition.\r\n\r\nSafe, without an account or identification data needed.\r\nFree of charge\r\n\r\nDownload now!",
    "descriptionHTML": "You are in the good place! <br><br>Doctor31 is an application that helps you find out what diseases you may suffer from. <br>You can consult it at any time. Whether you are at work, at home or on vacation. Whenever you want.<br><br>Use Doctor31 now to find out what your health condition is.<br>Use Doctor31 when you are not feeling well and find out what diseases you may be suffering from.<br>Use when you have blood, urine or stool tests results. Find out what they indicate.<br><br>Reliable information.<br>Doctor31 is created by doctors and uses the necessary information for them to obtain the right to practice in different specialties.<br><br>Easy to use.<br>Download the application and it is ready to use. You do not need an account, email or credit card.<br><br>Safe!<br>You use the application without any account or personal data that may lead to your identification.<br><br>Personalized information.<br>We provide you with information based on your symptoms, age, gender and medical history. We are all different from each other. That&#39;s why you receive information that suits you.<br><br>It&#39;s like a digital \u201cGeneral Practitioner (GP)\u201d on your phone.<br>It is a super doctor, having knowledge ranging from family medicine to surgery, from cardiology to dermatology. 31 main medical specialties. It helps you to keep calm, being informed whenever you want about your possible personal medical condition.<br><br>Safe, without an account or identification data needed.<br>Free of charge<br><br>Download now!",
    "summary": "An Symptom Cheker that helps you find out what diseases you may suffer from.",
    "installs": "10,000+",
    "minInstalls": 10000,
    "realInstalls": 10861,
    "score": 3,
    "ratings": 128,
    "reviews": 2,
    "histogram": [
        25,
        51,
        0,
        0,
        51
    ],
    "price": 0,
    "free": true,
    "currency": "USD",
    "sale": false,
    "saleTime": null,
    "originalPrice": null,
    "saleText": null,
    "offersIAP": false,
    "inAppProductPrice": null,
    "developer": "Doctor31",
    "developerId": "Doctor31",
    "developerEmail": "constantin@doctor31.com",
    "developerWebsite": "https://doctor31.com",
    "developerAddress": null,
    "privacyPolicy": "https://www.doctor31.com/privacy_page.php?lang=en",
    "genre": "Health & Fitness",
    "genreId": "HEALTH_AND_FITNESS",
    "categories": [
        {
            "name": "Health & Fitness",
            "id": "HEALTH_AND_FITNESS"
        }
    ],
    "icon": "https://play-lh.googleusercontent.com/1r5k8cVY9b57_ckFTQBDK-w3pAalh0BcUWSP7uvHR30gf44kZfV88NlS8okuA2TMycU",
    "headerImage": "https://play-lh.googleusercontent.com/m47n2gP4dDAFPYc_FwEmytmkuV9xHq15Ju_ISbZt3ZPgPU3eeGQKVQEENNxdd_yXLA",
    "screenshots": [
        "https://play-lh.googleusercontent.com/qYrF4b9gQe3VF7IXq3JVOUxIEbifSkPH49tpvHkwoQxMHFGqwbVHCnlYY2erxFH4kz4",
        "https://play-lh.googleusercontent.com/78lhf5mEbLKzmS0Vme8rFQ0pr5UoI-IjhXEqOXnTCDgKdC_pRzbZUHzETceBKiuGDA",
        "https://play-lh.googleusercontent.com/ja8EGUa-pvbaEyynjkpSJvrHJsRUfDoMcPJnHSbgIZ4v66TGLTABApbnmuTy4pWhpvY",
        "https://play-lh.googleusercontent.com/xTu-3wJEfxwve3D0ZUu_5tTPSzK0HYezpjRo29W37yk-3OxbjWeb3G5qB36SBltXX8-3",
        "https://play-lh.googleusercontent.com/ndM5DUl4MJCPWSYL77SNlvN1zAz_zMdYaHF-Z5AzUaSGpFrhhMVBXsWFzKAdG2vQ70Q",
        "https://play-lh.googleusercontent.com/bo7T5JjX3t1TAQuEwLsg_sS3aZdwWvLk_Qb6Be1Rl4OyLtSt-3Fd-ZoJ3vnWdM43vUP4",
        "https://play-lh.googleusercontent.com/2SW2w6mgvlrdIhbH5N2GRnTDA1FvrHu4G59qEmIukT7PzbZSX9ssi6vUH2cTP7IDAIo",
        "https://play-lh.googleusercontent.com/YlhJSnyyUhIf0RSBag4cf7_CUz03aIR5rPrtZnbd4xohDwFFrLGXtsYxuJ5LUn95vZQ"
    ],
    "video": "https://www.youtube.com/embed/nX_xuJj2Ur4?ps=play&vq=large&rel=0&autohide=1&showinfo=0",
    "videoImage": "https://play-lh.googleusercontent.com/m47n2gP4dDAFPYc_FwEmytmkuV9xHq15Ju_ISbZt3ZPgPU3eeGQKVQEENNxdd_yXLA",
    "contentRating": "Everyone",
    "contentRatingDescription": null,
    "adSupported": false,
    "containsAds": false,
    "released": "Jul 18, 2019",
    "lastUpdatedOn": "Oct 24, 2024",
    "updated": 1729796410,
    "version": "8.0.3",
    "comments": [],
    "appId": "com.ro.doctor31",
    "url": "https://play.google.com/store/apps/details?id=com.ro.doctor31&hl=en&gl=us"
}