{
    "title": "Skin Cancer Tracker",
    "description": "Skin Cancer Tracker enables you to track biopsies and procedures during your dermatology and Mohs surgery appointments. Store and compile images on your phone related to your skin cancer checks and skin cancer history in a readily accessible location with a sleek and minimalist design.\r\n\r\nFree App features:\r\n-Log feature for you to input pre-biopsy images and results in one place for ease of use and reference during dermatology follow-up appointments \r\n-My Skin Cancer History feature whereby skin cancer results are readily searchable\r\n-Monitoring tab to store images of specific lesions for reevaluation during dermatology follow up or during topical field therapy for precancerous lesions identified by your dermatologist\r\n-Appointment reminder for Mohs surgery date, suture removal, and dermatology follow up, which links to your phone alarm\r\n-Integrated links to Find a Surgeon accessed on the American College of Mohs Surgery website, American Academy of Dermatology dermatologist search feature, Mohs appropriate use criteria app, and skin cancer related resources\r\n-Images are stored locally to your phone\r\n-Bring this app to your next Mohs surgery or dermatology appointment. With Skin Cancer Tracker, take control of your skin health journey. Every photo, every entry, empowers you to track progress and embrace a future of informed decisions.",
    "descriptionHTML": "Skin Cancer Tracker enables you to track biopsies and procedures during your dermatology and Mohs surgery appointments. Store and compile images on your phone related to your skin cancer checks and skin cancer history in a readily accessible location with a sleek and minimalist design.<br><br>Free App features:<br>-Log feature for you to input pre-biopsy images and results in one place for ease of use and reference during dermatology follow-up appointments <br>-My Skin Cancer History feature whereby skin cancer results are readily searchable<br>-Monitoring tab to store images of specific lesions for reevaluation during dermatology follow up or during topical field therapy for precancerous lesions identified by your dermatologist<br>-Appointment reminder for Mohs surgery date, suture removal, and dermatology follow up, which links to your phone alarm<br>-Integrated links to Find a Surgeon accessed on the American College of Mohs Surgery website, American Academy of Dermatology dermatologist search feature, Mohs appropriate use criteria app, and skin cancer related resources<br>-Images are stored locally to your phone<br>-Bring this app to your next Mohs surgery or dermatology appointment. With Skin Cancer Tracker, take control of your skin health journey. Every photo, every entry, empowers you to track progress and embrace a future of informed decisions.",
    "summary": "Skin Cancer Tracker enables you to track biopsies & Mohs surgery",
    "installs": "50+",
    "minInstalls": 50,
    "realInstalls": 67,
    "score": null,
    "ratings": null,
    "reviews": null,
    "histogram": [
        0,
        0,
        0,
        0,
        0
    ],
    "price": 0,
    "free": true,
    "currency": "USD",
    "sale": false,
    "saleTime": null,
    "originalPrice": null,
    "saleText": null,
    "offersIAP": false,
    "inAppProductPrice": null,
    "developer": "NH Skin Cancer Surgery LLC",
    "developerId": "NH+Skin+Cancer+Surgery+LLC",
    "developerEmail": "info@nhskincancersurgery.com",
    "developerWebsite": "https://nhskincancersurgery.com/",
    "developerAddress": null,
    "privacyPolicy": "https://nhskincancersurgery.com/privacy-policy/",
    "genre": "Health & Fitness",
    "genreId": "HEALTH_AND_FITNESS",
    "categories": [
        {
            "name": "Health & Fitness",
            "id": "HEALTH_AND_FITNESS"
        }
    ],
    "icon": "https://play-lh.googleusercontent.com/prqOH97g5mpyED2StabRdKx09oxHnq6ie-YIapcp_bC0odT7avAxKqWfXPtks4sLTA",
    "headerImage": "https://play-lh.googleusercontent.com/5wV_a4GVMCP1eVeNZSdVx6yPaZQ64d8vGpzft2doEObFCnVfwBQTerOlpP8IBbG2eA",
    "screenshots": [
        "https://play-lh.googleusercontent.com/9jfFvOs9aFBHNVGzxAfvgmVJ2T5kwbe7IT-vFW2qlRCIRTt2dkfoJdK21amet6m1-4w",
        "https://play-lh.googleusercontent.com/i16OF9SgDvJKiQHUAkVZXUMe91q1C2PeoeZH59pva0JvcbDe3l1IKjs2a2fu3XfYjF8",
        "https://play-lh.googleusercontent.com/OdMYxsJprXhF0ILevZov2qoQzsyj0hISV_n8o0Ii3FunDvCC6Pe6yfIpSI_1Y4Y9d2zc",
        "https://play-lh.googleusercontent.com/N9b7SQq9HR9n2ZgZ4L6m_zNDdBSgYoad6moCMu0QVuDolRIBzugk7QYlWHIKTqRORNZK",
        "https://play-lh.googleusercontent.com/8Iib2jJPAworUcY74QnjDRyFlMlkRNdqEuOd0552CRPmNXDhNwe3EYJz1BtYmLUayw",
        "https://play-lh.googleusercontent.com/v7eINTG2k9q7ab8HFNi5AlPTJ7PBkUMbpI-CzRKAcqubAK581BYUtYKWCRTxBO84cio",
        "https://play-lh.googleusercontent.com/WhHZ9N9taauNIzL_3BpksbtIxad8BlMbGJDVCt8vGevfVr5lFYnBAUDNbWCHPUHcFlaw",
        "https://play-lh.googleusercontent.com/HEdZP0P-CH8fe452gKBqpdYU8RZatP3jjzVVXRbbKud5QMgRx82lU6ehbcnUhRCNer3p",
        "https://play-lh.googleusercontent.com/9yrnB0yaMWvcEY5xwRW4UA6wdvb-1mTugDNfenRqWLlxCrqHcJgWeuo1IxokPqsvUA8",
        "https://play-lh.googleusercontent.com/bo0M-cSeWwMktojn4f23D0PRAIQs32piwSTz_otagwMcOiYpCUla2fnDl1G0JUysmQ",
        "https://play-lh.googleusercontent.com/1RdNJ_NaScIAsVexOrU4g_A8J_-MvZa_DcoSuWlMendHMIZcnx6EAlifMJ5aLfikX98",
        "https://play-lh.googleusercontent.com/88m5MIAZsxSfB3mFR8f7WMf87TrJ_heCFsAjgNDv4Ud-1ONq1D9C9FpRnfjwac8RJA",
        "https://play-lh.googleusercontent.com/W60uLei28fvfntFJZ-ZKkfiWOOehuixxna48VBOcT1fETfQyJIsUsrMTnXmOMhkxNs0",
        "https://play-lh.googleusercontent.com/J1WWaahSznPmNGYrhForBjhyzEnCyIi0kEEmM5qxCm2r6Jmr8evkkPZmC2FYz9tkh7o",
        "https://play-lh.googleusercontent.com/uPLYXA9CSPCYVJ2SKong0pHMvKztLLPmPzUhPxC5XXUWbo6YtoHw_LVExEqzfLtZhV81",
        "https://play-lh.googleusercontent.com/e3wtNDSXLGkAeIqzrb2v-t6RCQG6PTWJGvhbLIqmO3SuFlGlgD0XQBPlA4Fb_AELK3E",
        "https://play-lh.googleusercontent.com/dnoGJHdXZOGUEgU3tDLnFEHvCT8AI25S7WDjcBbIf2R7jKYCZPFnsgYIlPX4oz0xcWg",
        "https://play-lh.googleusercontent.com/4PL0qfEPOETpnYsZwBUCg9CToOz44yPH-G6w-wHz0tS3gyhyYpQhOVInBtFOK_e_nA"
    ],
    "video": null,
    "videoImage": null,
    "contentRating": "Everyone",
    "contentRatingDescription": null,
    "adSupported": false,
    "containsAds": false,
    "released": "Jun 26, 2024",
    "lastUpdatedOn": "Jul 9, 2024",
    "updated": 1720541312,
    "version": "1.0.2",
    "comments": [],
    "appId": "com.hmapps.skin_cancer_tracker",
    "url": "https://play.google.com/store/apps/details?id=com.hmapps.skin_cancer_tracker&hl=en&gl=us"
}