{
    "title": "SIU Academy\u00ae",
    "description": "SIU Academy\u00ae App, the official mobile learning app of the Soci\u00e9t\u00e9 Internationale d\u2019Urologie (SIU), offers access to thousands of educational materials and activities published by SIU over the years such as eLearning Programs, Accredited Lectures, Self-Assessments, Learning Quizzes, Webinars, Asynchronous and live Webcasts, ePosters, Video Techniques, Documents, Abstracts, Expert opinion videos and editorials. \r\n\r\nYou may even interact with your peers through discussion forums at anytime while completing learning modules or viewing lectures. \r\n\r\nThe SIU Academy App also features a powerful search system allowing end-users to easily find precise content and much more to discover!\r\n\r\nSIU Academy\u00ae App is for SIU Members and other SIU Account holders (content restrictions may apply).\r\n\r\nShould you require technical support, please contact the SIU Academy\u00ae App support team at support@academy.siu-urology.org \r\n\r\n2018\u00a9 SIU. SIU Academy\u00ae App is a registered trademark of SIU.\r\n\r\nPublished under license from MULTILEARNING Group Inc.; SIU\u2019s digital education content provider.\r\n\r\n*requires an SIU Account, an internet connection, compatible Android devices and versions.",
    "descriptionHTML": "SIU Academy\u00ae App, the official mobile learning app of the Soci\u00e9t\u00e9 Internationale d\u2019Urologie (SIU), offers access to thousands of educational materials and activities published by SIU over the years such as eLearning Programs, Accredited Lectures, Self-Assessments, Learning Quizzes, Webinars, Asynchronous and live Webcasts, ePosters, Video Techniques, Documents, Abstracts, Expert opinion videos and editorials. <br><br>You may even interact with your peers through discussion forums at anytime while completing learning modules or viewing lectures. <br><br>The SIU Academy App also features a powerful search system allowing end-users to easily find precise content and much more to discover!<br><br>SIU Academy\u00ae App is for SIU Members and other SIU Account holders (content restrictions may apply).<br><br>Should you require technical support, please contact the SIU Academy\u00ae App support team at support@academy.siu-urology.org <br><br>2018\u00a9 SIU. SIU Academy\u00ae App is a registered trademark of SIU.<br><br>Published under license from MULTILEARNING Group Inc.; SIU\u2019s digital education content provider.<br><br>*requires an SIU Account, an internet connection, compatible Android devices and versions.",
    "summary": "The official Mobile Learning App of the Soci\u00e9t\u00e9 Internationale d\u2019Urologie",
    "installs": "1,000+",
    "minInstalls": 1000,
    "realInstalls": 2662,
    "score": null,
    "ratings": null,
    "reviews": null,
    "histogram": [
        0,
        0,
        0,
        0,
        0
    ],
    "price": 0,
    "free": true,
    "currency": "USD",
    "sale": false,
    "saleTime": null,
    "originalPrice": null,
    "saleText": null,
    "offersIAP": true,
    "inAppProductPrice": "$49.99 per item",
    "developer": "MULTILEARNING GROUP",
    "developerId": "MULTILEARNING+GROUP",
    "developerEmail": "support@academy.siu-urology.org",
    "developerWebsite": "http://academy.siu-urology.org",
    "developerAddress": "8782 RUE LAJEUNESSE\nMONTR\u00c9AL QC  H2M 1R6\nCANADA",
    "privacyPolicy": "https://academy.siu-urology.org/siu/policy/",
    "genre": "Education",
    "genreId": "EDUCATION",
    "categories": [
        {
            "name": "Education",
            "id": "EDUCATION"
        }
    ],
    "icon": "https://play-lh.googleusercontent.com/y1yXWA8uiIC8hetd6nxIX3Ar6-Wr5xqe-3nC5kefngce0mNKkElQkd_fmS3O7k62CbM",
    "headerImage": "https://play-lh.googleusercontent.com/BxXNSd2VxFXTQWJXeuKI184QNKZnrLjJa8OplfHPF73Q2q_cSIbmhrOEmkIqkZUiZQ",
    "screenshots": [
        "https://play-lh.googleusercontent.com/pVvlYIcvnV1pepfhpTmiBnr94QKzagWSS4RbhikIHkoqgxXTFkvLFCXi0YNYXFD47-s",
        "https://play-lh.googleusercontent.com/3puIArornv0GZ7IDWGWmsovkueTi8wkeUCgR2qjnv6EyOq0GHPbfQ4p8L7LqiznqLeU",
        "https://play-lh.googleusercontent.com/HceqNBV5eiJWQS8zfP6jUKRP4RumkjmwYvuLV57lFKUfAayGOGojhirD2WS89c1z",
        "https://play-lh.googleusercontent.com/8NzM-Ey8eK5yCpCszEMWIvvQBoxhh02UmQw9IAscGHgMakjL916AyRwjPJrVX1-Irxg",
        "https://play-lh.googleusercontent.com/BjifVEmliXprQyy0tx4I-lyBVziMC3f1Ymp_H4FPieeZMQxgoesaJY8vwmX8u1JgzOHm",
        "https://play-lh.googleusercontent.com/dRHhWm_5j536LSyCM62hXGQgFhuEDnmey7PoyYn87x67SFWYUUvVz4SeI6DgKUqtfaVF",
        "https://play-lh.googleusercontent.com/_GOmayAOgusyitmvZ3ABcwk-QcK6tTY174rl482hcQF8LN2NcpVsmVqtQBOr0__4rHE",
        "https://play-lh.googleusercontent.com/q4qqPh32D7OjUbib0u76c4xHW3kwrESoN1Sd9SF5nunb6ZiFCaDh14ezzzV2KN98iQ",
        "https://play-lh.googleusercontent.com/2GHD8CUjkZVFjUDwuUusQYGSt4jCrQAcrgExscb8fdJDStdbGGBYBtfNlIqKw7H419fW"
    ],
    "video": null,
    "videoImage": null,
    "contentRating": "Everyone",
    "contentRatingDescription": null,
    "adSupported": false,
    "containsAds": false,
    "released": "Oct 19, 2016",
    "lastUpdatedOn": "Jul 29, 2024",
    "updated": 1722284995,
    "version": "1.1.1.10",
    "comments": [],
    "appId": "com.multilearning.siuacademy",
    "url": "https://play.google.com/store/apps/details?id=com.multilearning.siuacademy&hl=en&gl=us"
}